{
  "m_GameObject": {
    "m_FileID": 0,
    "m_PathID": 2761119431389741140
  },
  "m_Enabled": 1,
  "m_Script": {
    "m_FileID": 0,
    "m_PathID": 2305682704411251456
  },
  "m_Name": "",
  "courseParams": [
    {
      "_paramType": 0,
      "_values": [
        3,
        200
      ],
      "_distance": 300.0
    },
    {
      "_paramType": 0,
      "_values": [
        4,
        200
      ],
      "_distance": 500.0
    },
    {
      "_paramType": 0,
      "_values": [
        1,
        200
      ],
      "_distance": 1050.0
    },
    {
      "_paramType": 0,
      "_values": [
        2,
        200
      ],
      "_distance": 1250.0
    },
    {
      "_paramType": 0,
      "_values": [
        3,
        200
      ],
      "_distance": 1800.0
    },
    {
      "_paramType": 0,
      "_values": [
        4,
        200
      ],
      "_distance": 2000.0
    },
    {
      "_paramType": 2,
      "_values": [
        1,
        2
      ],
      "_distance": 0.0
    },
    {
      "_paramType": 2,
      "_values": [
        2,
        2
      ],
      "_distance": 300.0
    },
    {
      "_paramType": 2,
      "_values": [
        1,
        1
      ],
      "_distance": 700.0
    },
    {
      "_paramType": 2,
      "_values": [
        2,
        1
      ],
      "_distance": 1050.0
    },
    {
      "_paramType": 2,
      "_values": [
        1,
        2
      ],
      "_distance": 1450.0
    },
    {
      "_paramType": 2,
      "_values": [
        2,
        2
      ],
      "_distance": 1800.0
    },
    {
      "_paramType": 2,
      "_values": [
        1,
        1
      ],
      "_distance": 2200.0
    },
    {
      "_paramType": 2,
      "_values": [
        2,
        1
      ],
      "_distance": 2500.0
    },
    {
      "_paramType": 4,
      "_values": [],
      "_distance": 2000.0
    },
    {
      "_paramType": 5,
      "_values": [],
      "_distance": 2010.0
    },
    {
      "_paramType": 8,
      "_values": [],
      "_distance": 2000.0
    },
    {
      "_paramType": 9,
      "_values": [],
      "_distance": 2010.0
    }
  ]
}